<parallel xmlns:xsi="http://www.w3.org/2001/XMLSchema-instance" xsi:noNamespaceSchemaLocation="parallel_texts.xsd">
    <text id="1.0">
        <sentence lang="prq">APIINKA</sentence>
        <sentence lang="es">EL SUCESOR DE INCA</sentence>
        <morphology format="ashaninkamorph" analysislevel="not-fully">


apiinka	[=apiinka][NRoot][=person's.name; Apu/Seer.Inca; Inca.person/people]

</morphology>
    </text>
    <text id="1.1">
        <sentence lang="prq" normalizationlevel="none">Sheeteni akarajetaiyeni maaroni nosaikajetzika.</sentence>
        <sentence lang="prq" normalizationlevel="normalized-alphabet">Sheeteni akarahetaiyeni maaroni nosaikahetzika.</sentence>
        <sentence lang="es">Buenas tardes a todos los que nos encontramos en este lugar.</sentence>
        <morphology format="ashaninkamorph" analysislevel="not-fully">


sheeteni	[=sheeteni][AdvRoot][=in.the.afternoon]

akarahetaiyeni	[a-][VPers][1PL.S/A+][--][=kara][VRoot][=COP.CAP (EN: the.amount,, to.be.Nº/#.in.number/quantity_of_sth.)][--][-he][NUM][+PL][=PL.S/A+; INTR: PL.S/A+; TR: PL.S/A+.or.+PL.O]he[--][-t][+EP]t[--][-aiy][+PL]aiy[--][-e+n.fut.][+REAL]e[--][-ni+circumfixing][+PL]

maaroni	[=maaroni][IndfPrn][=all, everyone]

nosaikahetzika	[no-][VPers][1SG.S/A+][--][=saik][VRoot][=to.be, to.be.at, to.be.in; to.sit; to.live][--][-a][+EP]a[--][-he][NUM][+PL][=PL.S/A+; INTR: PL.S/A+; TR: PL.S/A+.or.+PL.O]he[--][-tz][+EP]tz[--][-i+n.fut.][+REAL]i[--][-ka+proximal.loc.][+ADV]ka

.	.[$.]

</morphology>
        <parsing format="" analysislevel=""/>
    </text>
    <text id="1.2">
        <sentence lang="prq" normalizationlevel="none">Iroñaaka sheetenika nonkinkitsatakoteri aparoni ashaninka ikantaitziri Apiinka.</sentence>
        <sentence lang="prq" normalizationlevel="normalized-alphabet">Ironyaaka sheetenika nonkinkitsatakoteri aparoni ashaninka ikantaitziri Apiinka.</sentence>
        <sentence lang="es">Ahora en esta tarde, voy a contarles sobre una persona llamada Apiinka.</sentence>
        <morphology format="ashaninkamorph" analysislevel="not-fully">


ironyaaka	[=ironyaaka][AdvRoot][=now (ES: ahora)]

sheetenika	[=sheeteni][NRoot][=day][--][-ka+proximal.b.][Adv][+DEM][=here, close.to.the.speaker]

nonkinkitsatakoteri	[no-][VPers][1SG.S/A+][--][N=][IRR+][--][=kinkitsa][VRoot][=to.talk, to.tell (ES: contar, hablar, predicar)][--][-t][+EP]t[--][-ako][VS][+APPL.GEN][=GEN: with.reference.to.sth., about.sth.; INDR: action.affects.sth.in.an.indirect.manner]ako[--][-t][+EP]t[--][-e+n.fut.][+REAL]e[--][=ri][+3m.O]

aparoni	[=aparoni][NumeralPRQ][=one]

ashaninka	[=ashaninka][NRoot][=indigenous.person.that.lives.in.the.in.the.central.adjoining.Amazonian.regions.between.Peru-and-Brazil]

ikantaitziri	[i-][VPers][3m.S/A+][--][=kant][VRoot][=to.say; to.call;; to.do; to.happen;; to.be (ES: ser); to.be.able][--][-ai][+IMP.P][=3(PL)m.S/A+.is.unknown/unspecified-and-focus.on.+O]ai[--][-tz][+EP]tz[--][-i+n.fut.][+REAL]i[--][=ri][+3m.O]

apiinka	[=apiinka][NRoot][=person's.name; Apu/Seer.Inca; Inca.person/people]

.	.[$.]

</morphology>
        <parsing format="" analysislevel=""/>
    </text>
    <text id="1.3">
        <sentence lang="prq" normalizationlevel="none">Saikaintsirika aka anampikika paitachari Metaroki.</sentence>
        <sentence lang="prq" normalizationlevel="normalized-alphabet">Saikaintsirika aka anampikika paitachari Metaroki.</sentence>
        <sentence lang="es">Quién ha estado aquí por este lugar llamado Metaro.</sentence>
        <morphology format="ashaninkamorph" analysislevel="not-fully">


saikaintsirika	[=saik][VRoot][=to.be, to.be.at, to.be.in; to.sit; to.live][--][-aintsi][Asp][+STAT.PRF]aintsi[--][=ri][NS][+REL][--][-ka+proximal.loc.][+ADV]ka

aka	[=aka+proximal.b.][PrnDem][=here, close.to.the.speaker]

anampikika	[a-][NPers][1PL.poss+][--][=nampi][NRoot][=big.quantity][--][-ki][Cas][+LOC_LOC.T][--][-ka+proximal.b.][Adv][+DEM][=here, close.to.the.speaker]

paitachari	[=pai][VRoot][=to.be.called; to.call, to.name (ES: nombrar); to.get.white.hair][--][-t][+EP]t[--][-acha][Asp][+STAT.IPRF]acha[--][=ri][NS][+REL]

metaroki	[=Metaro][NRoot][=village's.name; flat, rounded.slightly.curved.area (ES: plato.de.barro)][--][-ki][Cas][+LOC_LOC.T]

.	.[$.]

</morphology>
        <parsing format="" analysislevel=""/>
    </text>
    <text id="1.4">
        <sentence lang="prq" normalizationlevel="none">Iroñaaka ikantajiro virakocha Metraro.</sentence>
        <sentence lang="prq" normalizationlevel="normalized-alphabet">Ironyaaka ikantahiro virakocha Metraro.</sentence>
        <sentence lang="es">Ahora la gente de afuera lo denomino Metraro.</sentence>
        <morphology format="ashaninkamorph" analysislevel="not-fully">


ironyaaka	[=ironyaaka][AdvRoot][=now (ES: ahora)]

ikantahiro	[i-][VPers][3m.S/A+][--][=kant][VRoot][=to.say; to.call;; to.do; to.happen;; to.be (ES: ser); to.be.able][--][-ah][ASP][+REGR_TERM][=REGR: to.repeat.sth.again, to.continue.sth.; TERM: finality-and-closure, once-and-for.all]ah[--][-i+n.fut.][+REAL]i[--][=ro][+3n.m.O]

virakocha	[=virakocha][NRoot][=outsider; white.person (PT: branco)]

metraro	[=Metraro][NRoot][=village's.name; rounded.slightly.curved.area (ES: plato.de.barro)]

.	.[$.]

</morphology>
        <parsing format="" analysislevel=""/>
    </text>
    <text id="1.5">
        <sentence lang="prq" normalizationlevel="none">Yoka ashaninka osheki yaaki atziri, osheki yaaki atzirive.</sentence>
        <sentence lang="prq" normalizationlevel="normalized-alphabet">Yoka ashaninka osheki yaaki atziri, osheki yaaki atzirive.</sentence>
        <sentence lang="es">Este paisano juntó a muchas personas, ¡a muchas personas juntó!</sentence>
        <morphology format="ashaninkamorph" analysislevel="not-fully">


yoka	[=yoka+m.+proximal][PrnDem][=this (ES: él.aquí, ellos.aquí)]

ashaninka	[=ashaninka][NRoot][=indigenous.person.that.lives.in.the.in.the.central.adjoining.Amazonian.regions.between.Peru-and-Brazil]

osheki	[=osheki][AdjRoot][=many; much; a.lot]

yaaki	[y-][VPers][3m.S/A+][--][=a][VRoot][=to.get][--][-ak][ASP][+PRF][=completed.actn.; FUT:actn.viewed.as.being.completed]ak[--][-i+n.fut.][+REAL]i

atziri	[=atziri+m.+poss@te.][NRoot][=person, individual, human (ES: gente)]

,	,[$.]

osheki	[=osheki][AdjRoot][=many; much; a.lot]

yaaki	[y-][VPers][3m.S/A+][--][=a][VRoot][=to.get][--][-ak][ASP][+PRF][=completed.actn.; FUT:actn.viewed.as.being.completed]ak[--][-i+n.fut.][+REAL]i

atzirive	[=atziri+m.+poss@te.][NRoot][=person, individual, human (ES: gente)][--][=ve][+EXCL][=exclaiming,announcing]

.	.[$.]

</morphology>
        <parsing format="" analysislevel=""/>
    </text>
    <text id="1.6">
        <sentence lang="prq" normalizationlevel="none">Yapototakiri, yapotojetakiri maaroni okanta yantavaitakantyaariri.</sentence>
        <sentence lang="prq" normalizationlevel="normalized-alphabet">Yapototakiri, yapotohetakiri maaroni okanta yantavaitakantyaariri.</sentence>
        <sentence lang="es">Los juntó, reunió a todo, para que les haga trabajar.</sentence>
        <morphology format="ashaninkamorph" analysislevel="not-fully">


yapototakiri	[y-][VPers][3m.S/A+][--][=apoto][VRoot][=to.gather (ES: juntar), to.meet, to.get.together][--][-t][+EP]t[--][-ak][ASP][+PRF][=completed.actn.; FUT:actn.viewed.as.being.completed]ak[--][-i+n.fut.][+REAL]i[--][=ri][+3m.O]

,	,[$.]

yapotohetakiri	[y-][VPers][3m.S/A+][--][=apoto][VRoot][=to.gather (ES: juntar), to.meet, to.get.together][--][-he][NUM][+PL][=PL.S/A+; INTR: PL.S/A+; TR: PL.S/A+.or.+PL.O]he[--][-t][+EP]t[--][-ak][ASP][+PRF][=completed.actn.; FUT:actn.viewed.as.being.completed]ak[--][-i+n.fut.][+REAL]i[--][=ri][+3m.O]

maaroni	[=maaroni][AdjRoot][=everybody, all, entire]

okanta	[o-][VPers][3n.m.S/A+][--][=kant][VRoot][=to.say; to.call;; to.do; to.happen;; to.be (ES: ser); to.be.able][--][-a+n.fut.][+REAL]a

yantavaitakantyaariri	[y-][VPers][3m.S/A+][--][=antavai][VRoot][=to.work (ES: trabajar)][--][-t][+EP]t[--][-ak][+CAUS.SOC][=to.cause.sth/sb.to.do.sth.; to.make.sth/sb.to.do.sth.]ak[--][-ant][Asp][+APPL.REAS][=in.order.to, so.that (ES: para.que)]ant[--][-yaa+fut.][+IRR]yaa[--][=ri][+3m.O][--][=ri][NS][+REL]

.	.[$.]

</morphology>
        <parsing format="" analysislevel=""/>
    </text>
    <text id="1.7">
        <sentence lang="prq" normalizationlevel="none">Ari okantavitaka kameetsa, yantavaitakakiri, ipankitakakiri ishinkini, imachakite, iyaniri, ivaryantzitepaye, iyokani, irinkini.</sentence>
        <sentence lang="prq" normalizationlevel="normalized-alphabet">Ari okantavitaka kameetsa, yantavaitakakiri, ipankitakakiri ishinkini, imachakite, iyaniri, ivaryantzitepaye, iyokani, irinkini.</sentence>
        <sentence lang="es">Hasta aquí estaba muy bien, los hizo trabajar, les hizo sembrar su maiz, sus frijoles, sus yucas, sus plátanos, sus cocos, sis maníes.</sentence>
        <morphology format="ashaninkamorph" analysislevel="not-fully">


ari	[=ari][PostPol][=PP][=there; so; thus; thereby; just.like.that (ES: así.es); to.be.this.way (ES: ser.así)]

okantavitaka	[o-][VPers][3n.m.S/A+][--][=kant][VRoot][=to.say; to.call;; to.do; to.happen;; to.be (ES: ser); to.be.able][--][-a][+EP]a[--][-vit][+FRUS][=unsuccessful/interrupted.action/state (EN: in.vain; ES: casi); action.that.didn't.achieve.the.desired.result]vit[--][-ak][ASP][+PRF][=completed.actn.; FUT:actn.viewed.as.being.completed]ak[--][-a+fut.][+IRR]a

kameetsa	[=kameetsa][NRoot][=well (ES: bien)]

,	,[$.]

yantavaitakakiri	[y-][VPers][3m.S/A+][--][=ant][VRoot][=to.beat, to.hit; to.build, to.do, to.make][--][-a][+EP]a[--][-vai][ASP][+DUR][=action/state.endured.over.a.long.period.of.time; motion.took.place.over.a.long.distance]vai[--][-t][+EP]t[--][-ak][+CAUS.SOC][=to.cause.sth/sb.to.do.sth.; to.make.sth/sb.to.do.sth.]ak[--][-ak][ASP][+PRF][=completed.actn.; FUT:actn.viewed.as.being.completed]ak[--][-i+n.fut.][+REAL]i[--][=ri][+3m.O]

,	,[$.]

ipankitakakiri	[i-][VPers][3m.S/A+][--][=panki][VRoot][=to.plant, to.sow (ES: sembrar)][--][-t][+EP]t[--][-ak][+CAUS.SOC][=to.cause.sth/sb.to.do.sth.; to.make.sth/sb.to.do.sth.]ak[--][-ak][ASP][+PRF][=completed.actn.; FUT:actn.viewed.as.being.completed]ak[--][-i+n.fut.][+REAL]i[--][=ri][+3m.O]


</morphology>
        <parsing format="" analysislevel=""/>
    </text>
    <text id="1.8">
        <sentence lang="prq">Osheki ipankitakajetakiri atziripaye arika yante ovantsi.</sentence>
        <sentence lang="es">Los hizo sembrar mucho cuando abrían una chacra.</sentence>
        <morphology format="" analysislevel=""/>
        <parsing format="" analysislevel=""/>
    </text>
    <text id="1.9">
        <sentence lang="prq">Ityaankiri aparopaye: “Aviroka antatsini ovantsi, aviroka jatatsini antamiki, pamini vatsatsi avyari.”</sentence>
        <sentence lang="es">Envía a cada uno: “Tú vas a hacer el rozo, tú te vas al monte a buscar carne para comer.”</sentence>
        <morphology format="" analysislevel=""/>
        <parsing format="" analysislevel=""/>
    </text>
    <text id="1.10">
        <sentence lang="prq">Ari okantajetakari, kooyapaye iroo kotsivaitatsini, eentsipaye ontzimatye yamitakoteri irora inkoyavaite.</sentence>
        <sentence lang="es">Así fue todo: las mujeres van a cocinar, los niños tienen que ayudar a recoger hojitos.</sentence>
        <morphology format="" analysislevel=""/>
        <parsing format="" analysislevel=""/>
    </text>
    <text id="1.11">
        <sentence lang="prq">Ikanta iyoka Apiinkaka osheki inintavitakari, poñaashitaka avisaki osheki osarentsi.</sentence>
        <sentence lang="es">Ahora este Apiinka muchos lo estimaban, después de muchos años.</sentence>
        <morphology format="" analysislevel=""/>
        <parsing format="" analysislevel=""/>
    </text>
    <text id="1.12">
        <sentence lang="prq">Iroñaaka Apiinkaka katsimaritaji, te ininte aavatsate kapicheeni, aavatsate intaani avya kapicheeni.</sentence>
        <sentence lang="es">Ahora este sucesor del inca se volvió malo, no quería que comiéramos mucho, deberíamos comer un poquito, poquita comida debemos comer.</sentence>
        <morphology format="" analysislevel=""/>
        <parsing format="" analysislevel=""/>
    </text>
    <text id="1.13">
        <sentence lang="prq">Kanirikya ashamokotzitakyaro osheki avanteki, irima vatsatsi ontzimatye ampitsari kapicheeni.</sentence>
        <sentence lang="es">La yuca deberíamos llenar la boca grande, pero la carne tenemos que pedaciarla poquito.</sentence>
        <morphology format="" analysislevel=""/>
        <parsing format="" analysislevel=""/>
    </text>
    <text id="1.14">
        <sentence lang="prq">Aniyantyaariri ninkarika iñaakotakai aavatsatatsini, tzimatsi isorarotepaye katziyavintariri aminatsiri.</sentence>
        <sentence lang="es">Comemos más rápido antes que nos miren sus soldados que son parados y están vigilando.</sentence>
        <morphology format="" analysislevel=""/>
        <parsing format="" analysislevel=""/>
    </text>
    <text id="1.15">
        <sentence lang="prq">Kantzimanintakiriri o pinkatsaryanintakiriri irotaki yaiteri imposaiteri, inchekaiteri intsatsinkakeri irora ikentsi.</sentence>
        <sentence lang="es">Alguien habla mal de él o lo desobedeció, ya está sentenciado a ser golpeado o cortado, decapitado el cuello.</sentence>
        <morphology format="" analysislevel=""/>
        <parsing format="" analysislevel=""/>
    </text>
    <text id="1.16">
        <sentence lang="prq">Maatsi osheki ashaninka aisatzi, osheki aisatzi ivaki.</sentence>
        <sentence lang="es">Hubo bastante gente también, hubiéran muchos que ha matado.</sentence>
        <morphology format="" analysislevel=""/>
        <parsing format="" analysislevel=""/>
    </text>
    <text id="1.17">
        <sentence lang="prq">Ashaninkapatsaini tera iyotatye ivavaitya yaavatsavaitapaki, kantanaki aminakovintziri.</sentence>
        <sentence lang="es">Como no sabían los paisanos comer poco, comían rápido, hasta que los observaron los vigilantes.</sentence>
        <morphology format="" analysislevel=""/>
        <parsing format="" analysislevel=""/>
    </text>
    <text id="1.18">
        <sentence lang="prq">Maatsi aka aparoni irora, piyatsatakamiri yamaitakari, maatsi itotamento ivisamento ivakiri ikintsiki itsatsinkaryakeri.</sentence>
        <sentence lang="es">Hay aquí una persona que te desobedeció, lo traen a esa persona; tiene Apiinka un cortador para cortar el cuello, de inmediato está decapitado.</sentence>
        <morphology format="" analysislevel=""/>
        <parsing format="" analysislevel=""/>
    </text>
    <text id="1.19">
        <sentence lang="prq">Yaaitanakiri inkitaiteri, ari ikanta ashaninkapaye.</sentence>
        <sentence lang="es">Lo llevan a enterrar, así pasaban los paisanos.</sentence>
        <morphology format="" analysislevel=""/>
        <parsing format="" analysislevel=""/>
    </text>
    <text id="1.20">
        <sentence lang="prq">Iroñaaka maaroni tsarovajetaki, inkimavakeri inkaime maaroni jatajetanakive!</sentence>
        <sentence lang="es">Ahora todos tenían miedo, cuando lo escuchaban gritar [llamar], todo se reunían de inmediato.</sentence>
        <morphology format="" analysislevel=""/>
        <parsing format="" analysislevel=""/>
    </text>
    <text id="1.21">
        <sentence lang="prq">Ari okantatya itsaronkakini ikantajetaki.</sentence>
        <sentence lang="es">Así estaba con miedo cada uno.</sentence>
        <morphology format="" analysislevel=""/>
        <parsing format="" analysislevel=""/>
    </text>
    <text id="1.22">
        <sentence lang="prq">Tsika akanterika? Tekatsi ankanteri.</sentence>
        <sentence lang="es">¿Cómo vamos a hacerlo? No podemos hacer nada.</sentence>
        <morphology format="" analysislevel=""/>
        <parsing format="" analysislevel=""/>
    </text>
    <text id="1.23">
        <sentence lang="prq">Arika inkimake ninkarika kantzimanintakiriri, irotaki intsatsinkatakeri.</sentence>
        <sentence lang="es">Cuando escucha algun comentario, está sentenciado a ser degollado.</sentence>
        <morphology format="" analysislevel=""/>
        <parsing format="" analysislevel=""/>
    </text>
    <text id="1.24">
        <sentence lang="prq">Iroñaaka iyoka Apiinkaka maatsi ivanko, isaikashita apaniroini, itsatamento isaikantari, ari isaiki anta.</sentence>
        <sentence lang="es">Ahora este sucesor de inca tiene una casa, vive solito colgado de su degollador, ahí vive, allá.</sentence>
        <morphology format="" analysislevel=""/>
        <parsing format="" analysislevel=""/>
    </text>
    <text id="1.25">
        <sentence lang="prq">Ontzimatye irora amontyaanake, maatsi aparoni tsatainchari, apite inchato, aitaki ankinanakeri, ampampyaatanakiro, ampampyaatantyarori ariitantyaari ivankoki.</sentence>
        <sentence lang="es">Tenemos que este [puente] cruzar, hay uno que está colgado, dos palos por allí, por allí vamos a pasar, hay que caminar sobre esos palos para llegar a su casa.</sentence>
        <morphology format="" analysislevel=""/>
        <parsing format="" analysislevel=""/>
    </text>
    <text id="1.26">
        <sentence lang="prq">Ontzimatye anaryaapainte, airorika anaryaashitari, airorika avitsatari irotaki intsatsinkavakai.</sentence>
        <sentence lang="es">Tenemos que echarnos en el suelo, si no nos echamos en el suelo, or si no le saludamos, de inmediato nos corta el cuello.</sentence>
        <morphology format="" analysislevel=""/>
        <parsing format="" analysislevel=""/>
    </text>
    <text id="1.27">
        <sentence lang="prq">Iroñaaka ipokantakari apite kishiisatzi ikantapakiri aparoni asheninka.</sentence>
        <sentence lang="es">Ahora cuando vinieron dos pajonalinos, le dijeron a nuestro paisano.</sentence>
        <morphology format="" analysislevel=""/>
        <parsing format="" analysislevel=""/>
    </text>
    <text id="1.28">
        <sentence lang="prq">“Noshaninka, tzimatsi piyokani?” Yakanaki: “Je, tzimatsi.”</sentence>
        <sentence lang="es">“Paisano, ¿tienes tu coca?” Le contestó: “Sí, tengo.”</sentence>
        <morphology format="" analysislevel=""/>
        <parsing format="" analysislevel=""/>
    </text>
    <text id="1.29">
        <sentence lang="prq">Tzimakotatsi Apiinkanta iri tzimakotatsi maaroni.</sentence>
        <sentence lang="es">Él que tiene más es este Apiinka, es él que tiene todo.</sentence>
        <morphology format="" analysislevel=""/>
        <parsing format="" analysislevel=""/>
    </text>
    <text id="1.30">
        <sentence lang="prq">“A-a, ja, ari impakina.”</sentence>
        <sentence lang="es">“Ja, ja, me la va a dar.”</sentence>
        <morphology format="" analysislevel=""/>
        <parsing format="" analysislevel=""/>
    </text>
    <text id="1.31">
        <sentence lang="prq">”Je, aritaki impakimi.”</sentence>
        <sentence lang="es">“Sí, sí, te la va a dar [coca].”</sentence>
        <morphology format="" analysislevel=""/>
        <parsing format="" analysislevel=""/>
    </text>
    <text id="1.32">
        <sentence lang="prq">“Intsitya nojateta.”</sentence>
        <sentence lang="es">“Voy a ir.”</sentence>
        <morphology format="" analysislevel=""/>
        <parsing format="" analysislevel=""/>
    </text>
    <text id="1.33">
        <sentence lang="prq">Yakanakiri: “Je, pijate, piñaapanteri.”</sentence>
        <sentence lang="es">Le contestó, “Sí, anda, visítalo.”</sentence>
        <morphology format="" analysislevel=""/>
        <parsing format="" analysislevel=""/>
    </text>
    <text id="1.34">
        <sentence lang="prq">Te inkanterikya: “Tekira pariitzimotyaarita, ari irorave, pijataki, ontzimatye pintyerovashitapakyaari onkantya impantyaamiri iyokanira.”</sentence>
        <sentence lang="es">No le dijo, “Lo que deberías hacer antes de llegar, este, vaya, tienes que arrodillarte para que te dé su coca.”</sentence>
        <morphology format="" analysislevel=""/>
        <parsing format="" analysislevel=""/>
    </text>
    <text id="1.35">
        <sentence lang="prq">Iroñaaka iyoka apiteroite kishiisatzika avisanaki, tzimatsi ichakopite, ivyamini.</sentence>
        <sentence lang="es">Ahora estos dos pajonalinos pasaron [en visita al Apiinka], tenían sus arcos y flechas.</sentence>
        <morphology format="" analysislevel=""/>
        <parsing format="" analysislevel=""/>
    </text>
    <text id="1.36">
        <sentence lang="prq">Ivyamini antarove-e!</sentence>
        <sentence lang="es">¡Arcos muy gruesos y grandes!</sentence>
        <morphology format="" analysislevel=""/>
        <parsing format="" analysislevel=""/>
    </text>
    <text id="1.37">
        <sentence lang="prq">Ikantzi: “Tsika isaikika?” Ikantzi: “Jiri isaikinta.”</sentence>
        <sentence lang="es">Dijo: “¿Dónde vive Apiinka?” Le contestó: “Allá está sentado.”</sentence>
        <morphology format="" analysislevel=""/>
        <parsing format="" analysislevel=""/>
    </text>
    <text id="1.38">
        <sentence lang="prq">Iñaapakiri, jataki.</sentence>
        <sentence lang="es">Lo vio y se fue.</sentence>
        <morphology format="" analysislevel=""/>
        <parsing format="" analysislevel=""/>
    </text>
    <text id="1.39">
        <sentence lang="prq">Ikaimapaki, ikantzi: “Pinkatsari!”</sentence>
        <sentence lang="es">[Antes de llegar] gritó, dijo: “Jefe-e!”</sentence>
        <morphology format="" analysislevel=""/>
        <parsing format="" analysislevel=""/>
    </text>
    <text id="1.40">
        <sentence lang="prq">Ikantziri: “Pavishi.”</sentence>
        <sentence lang="es">El jefe contestó: “Pasa.”</sentence>
        <morphology format="" analysislevel=""/>
        <parsing format="" analysislevel=""/>
    </text>
    <text id="1.41">
        <sentence lang="prq">Te intyerovimotapakyaari, iro yariitapakitya.</sentence>
        <sentence lang="es">No se había arrodillado más antes cuando estaba llegando.</sentence>
        <morphology format="" analysislevel=""/>
        <parsing format="" analysislevel=""/>
    </text>
    <text id="1.42">
        <sentence lang="prq">kantziri: “Pinkatsari, nonintaitatzi piyokani.”</sentence>
        <sentence lang="es">Le dijo al jefe: “Jefe, yo quisiera tu coca.”</sentence>
        <morphology format="" analysislevel=""/>
        <parsing format="" analysislevel=""/>
    </text>
    <text id="1.43">
        <sentence lang="prq">Isaikatzira Apiinkara iñaavakiri, te intyerovimotapakyaari, kisanaka.</sentence>
        <sentence lang="es">Cuando Apiinka que estaba sentado vio al pajonalino que no se arrodilló ante él, se enojó.</sentence>
        <morphology format="" analysislevel=""/>
        <parsing format="" analysislevel=""/>
    </text>
    <text id="1.44">
        <sentence lang="prq"> “Ah, pinintatzi irora koka?”</sentence>
        <sentence lang="es">“¿Lo que quieres es la coca?”</sentence>
        <morphology format="" analysislevel=""/>
        <parsing format="" analysislevel=""/>
    </text>
    <text id="1.45">
        <sentence lang="prq">Yaanakiro yashirotsate, irora itotamento.</sentence>
        <sentence lang="es">Cogió su alambre, este, su cortador.</sentence>
        <morphology format="" analysislevel=""/>
        <parsing format="" analysislevel=""/>
    </text>
    <text id="1.46">
        <sentence lang="prq">“Iroka pinintziri?”</sentence>
        <sentence lang="es">“¿Este es lo qué quieres?”</sentence>
        <morphology format="" analysislevel=""/>
        <parsing format="" analysislevel=""/>
    </text>
    <text id="1.47">
        <sentence lang="prq">Yairikakotavakeri, tsinik.</sentence>
        <sentence lang="es">Le agarró de la mano con su cortador.</sentence>
        <morphology format="" analysislevel=""/>
        <parsing format="" analysislevel=""/>
    </text>
    <text id="1.48">
        <sentence lang="prq">“Tsikama opaitaka pinintziri?”</sentence>
        <sentence lang="es">[Apiinka preguntó al visitante:] “¿Qué es lo que quieres?”</sentence>
        <morphology format="" analysislevel=""/>
        <parsing format="" analysislevel=""/>
    </text>
    <text id="1.49">
        <sentence lang="prq">Yairikajetakiri, katziyanaka, yairikajetakirira.</sentence>
        <sentence lang="es">Le agarraron sus manos los dos pajonalinos, se levantó como ya lo tenía agarrado.</sentence>
        <morphology format="" analysislevel=""/>
        <parsing format="" analysislevel=""/>
    </text>
    <text id="1.50">
        <sentence lang="prq">Iroñaaka iposakirira iminkyantanakaniri pyamini itziyamoroki.</sentence>
        <sentence lang="es">Ahora lo golpearon, introdujeron por su ano el arco.</sentence>
        <morphology format="" analysislevel=""/>
        <parsing format="" analysislevel=""/>
    </text>
    <text id="1.51">
        <sentence lang="prq">Ari imisaikanakiri, yaaitanakiniri, yaanaki osheki irora iyokani.</sentence>
        <sentence lang="es">Allí lo hicieron sentar, se lo llevaron, llevaron bastante esta coca.</sentence>
        <morphology format="" analysislevel=""/>
        <parsing format="" analysislevel=""/>
    </text>
    <text id="1.52">
        <sentence lang="prq">Jataji, iro iviraja pankotsiki ikantapaji: “Piyajanave!”</sentence>
        <sentence lang="es">Se fueron, cuando llegó a la casa, el pajonalino dijo: “¡Ya he vuelto!”</sentence>
        <morphology format="" analysislevel=""/>
        <parsing format="" analysislevel=""/>
    </text>
    <text id="1.53">
        <sentence lang="prq">Ikantziri: “Iroñaaka atzirira kantavakeriri inkaranki, tzimatsi iyokani.”</sentence>
        <sentence lang="es">Dijo: “La persona de que le dijo recién tenía su coca.”</sentence>
        <morphology format="" analysislevel=""/>
        <parsing format="" analysislevel=""/>
    </text>
    <text id="1.54">
        <sentence lang="prq">“Piñaapaintziri?”</sentence>
        <sentence lang="es">“¿Lo visitaste?”</sentence>
        <morphology format="" analysislevel=""/>
        <parsing format="" analysislevel=""/>
    </text>
    <text id="1.55">
        <sentence lang="prq">“Je, noñaapaintziri, irotaki nompiyaje.”</sentence>
        <sentence lang="es">“Sí, yo lo he visitado, ya voy a regresar.”</sentence>
        <morphology format="" analysislevel=""/>
        <parsing format="" analysislevel=""/>
    </text>
    <text id="1.56">
        <sentence lang="prq">Jatzi atziri, tera ayotatyeri, jataji.</sentence>
        <sentence lang="es">Regresó el hombre como no le conocían, regresó.</sentence>
        <morphology format="" analysislevel=""/>
        <parsing format="" analysislevel=""/>
    </text>
    <text id="1.57">
        <sentence lang="prq">Ikanta iñaavitari, avisanaki aparoni kitaiteri, irojatzi apitetanaki kitaiteri isaiki.</sentence>
        <sentence lang="es">Ahora lo veían sentado, pasó un día, seguía sentado, pasó el segundo día [después de visita por parte de los pajonalinos].</sentence>
        <morphology format="" analysislevel=""/>
        <parsing format="" analysislevel=""/>
    </text>
    <text id="1.58">
        <sentence lang="prq">Mavatapaintziri iñaatziri amemporipaye irora ishonka, ishonkataka.</sentence>
        <sentence lang="es">Cuando se aproximaban el tercer día, vieron gallinazos blancos volar, sobrevolar.</sentence>
        <morphology format="" analysislevel=""/>
        <parsing format="" analysislevel=""/>
    </text>
    <text id="1.59">
        <sentence lang="prq">Yaminaitziri: “Tsikama opaitatyaka?</sentence>
        <sentence lang="es">Se fueron a ver qué es lo que pasaba.</sentence>
        <morphology format="" analysislevel=""/>
        <parsing format="" analysislevel=""/>
    </text>
    <text id="1.60">
        <sentence lang="prq">Tsikama otzimatsika iroñaaka yoka anta shitsivari?</sentence>
        <sentence lang=""/>
        <morphology format="" analysislevel=""/>
        <parsing format="" analysislevel=""/>
    </text>
    <text id="1.61">
        <sentence lang="prq">Intsitya aminaiteri!”</sentence>
        <sentence lang=""/>
        <morphology format="" analysislevel=""/>
        <parsing format="" analysislevel=""/>
    </text>
    <text id="1.62">
        <sentence lang="prq">Jaitetzi, yaminaitziri, yokaakitaitari iñaatziri.</sentence>
        <sentence lang=""/>
        <morphology format="" analysislevel=""/>
        <parsing format="" analysislevel=""/>
    </text>
    <text id="1.63">
        <sentence lang="prq">Kiryaasontokitakive!</sentence>
        <sentence lang=""/>
        <morphology format="" analysislevel=""/>
        <parsing format="" analysislevel=""/>
    </text>
    <text id="1.64">
        <sentence lang="prq">Kamaki.</sentence>
        <sentence lang=""/>
        <morphology format="" analysislevel=""/>
        <parsing format="" analysislevel=""/>
    </text>
    <text id="1.65">
        <sentence lang="prq">Ivyamini itziyamoroki isaantaitanakiri.</sentence>
        <sentence lang=""/>
        <morphology format="" analysislevel=""/>
        <parsing format="" analysislevel=""/>
    </text>
    <text id="1.66">
        <sentence lang="prq">Isaikakotaki, atziripaye iroñaaka kimoshiri ikantanakave!</sentence>
        <sentence lang=""/>
        <morphology format="" analysislevel=""/>
        <parsing format="" analysislevel=""/>
    </text>
    <text id="1.67">
        <sentence lang="prq">Kimoshiri ikantajetanaja.</sentence>
        <sentence lang=""/>
        <morphology format="" analysislevel=""/>
        <parsing format="" analysislevel=""/>
    </text>
    <text id="1.68">
        <sentence lang="prq">Iroñakya ivaitakiri.</sentence>
        <sentence lang=""/>
        <morphology format="" analysislevel=""/>
        <parsing format="" analysislevel=""/>
    </text>
    <text id="1.69">
        <sentence lang="prq">Isoratotepaye piyavintapintariri, shiyajetanaka irirori.</sentence>
        <sentence lang=""/>
        <morphology format="" analysislevel=""/>
        <parsing format="" analysislevel=""/>
    </text>
    <text id="1.70">
        <sentence lang="prq">Ikovi itzinanajemi pashini, te inkantaji, jatzi, itsonka atziri, ijataji.</sentence>
        <sentence lang=""/>
        <morphology format="" analysislevel=""/>
        <parsing format="" analysislevel=""/>
    </text>
    <text id="1.71">
        <sentence lang="prq">Kimoshiritanaji atziripaye, osheki ivaki itomipatsaini, eentsitepatsaini.</sentence>
        <sentence lang=""/>
        <morphology format="" analysislevel=""/>
        <parsing format="" analysislevel=""/>
    </text>
    <text id="1.72">
        <sentence lang="prq">Iroñaaka atziripaye ikinashijetanaja pashini kirinka, pashini katonko, pashini ikinashijetanajya.</sentence>
        <sentence lang=""/>
        <morphology format="" analysislevel=""/>
        <parsing format="" analysislevel=""/>
    </text>
    <text id="1.73">
        <sentence lang="prq">Te yampototanajya.</sentence>
        <sentence lang=""/>
        <morphology format="" analysislevel=""/>
        <parsing format="" analysislevel=""/>
    </text>
    <text id="1.74">
        <sentence lang="prq">Ari okaratzi, akimakoventziri iroka Apiinka ikanta pairani.</sentence>
        <sentence lang=""/>
        <morphology format="" analysislevel=""/>
        <parsing format="" analysislevel=""/>
    </text>
    <text id="1.75">
        <sentence lang="prq">Paasonki.</sentence>
        <sentence lang=""/>
        <morphology format="" analysislevel=""/>
        <parsing format="" analysislevel=""/>
    </text>
</parallel>
